minerva/.DS_Store
minerva/README.md
minerva/__init__.py
minerva/build_dataset.py
minerva/model.py
minerva/train_distributed.py
minerva/utils.py
minerva_torch-0.0.1.dist-info/LICENSE
minerva_torch-0.0.1.dist-info/WHEEL
minerva_torch-0.0.1.dist-info/METADATA
minerva_torch-0.0.1.dist-info/RECORD
