Metadata-Version: 2.1
Name: minerva-torch
Version: 0.0.1
Summary: Transformers at zeta scales
Home-page: https://github.com/kyegomez/Minerva
License: MIT
Keywords: Transformers,zeta scale
Author: Zeta Team
Author-email: kye@apac.ai
Requires-Python: >=3.8,<4.0
Classifier: License :: OSI Approved :: MIT License
Classifier: Programming Language :: Python :: 3
Classifier: Programming Language :: Python :: 3.8
Classifier: Programming Language :: Python :: 3.9
Classifier: Programming Language :: Python :: 3.10
Classifier: Programming Language :: Python :: 3.11
Classifier: Programming Language :: Python :: 3
Requires-Dist: accelerate
Requires-Dist: torch
Requires-Dist: transformers
Requires-Dist: zetascale
